reqless/__init__.py
reqless/__version__.py
reqless/config.py
reqless/exceptions.py
reqless/importer.py
reqless/job.py
reqless/listener.py
reqless/logger.py
reqless/proctitle.py
reqless/profile.py
reqless/py.typed
reqless/queue.py
reqless/throttle.py
reqless/util.py
reqless/abstract/__init__.py
reqless/abstract/abstract_client.py
reqless/abstract/abstract_config.py
reqless/abstract/abstract_job.py
reqless/abstract/abstract_job_data.py
reqless/abstract/abstract_job_processor.py
reqless/abstract/abstract_jobs.py
reqless/abstract/abstract_queue.py
reqless/abstract/abstract_queue_identifiers_transformer.py
reqless/abstract/abstract_queue_jobs.py
reqless/abstract/abstract_queue_resolver.py
reqless/abstract/abstract_queues.py
reqless/abstract/abstract_throttle.py
reqless/abstract/abstract_throttles.py
reqless/abstract/abstract_workers.py
reqless/lua/qless-lib.lua
reqless/lua/qless.lua
reqless/qmore/__init__.py
reqless/qmore/client.py
reqless/queue_resolvers/__init__.py
reqless/queue_resolvers/qmore_dynamic_mapping_queue_identifiers_transformer.py
reqless/queue_resolvers/qmore_dynamic_priority_queue_identifiers_transformer.py
reqless/queue_resolvers/transforming_queue_resolver.py
reqless/workers/__init__.py
reqless/workers/forking.py
reqless/workers/greenlet.py
reqless/workers/serial.py
reqless/workers/util.py
reqless/workers/worker.py
reqless-0.13.3.data/scripts/reqless-py-worker
reqless-0.13.3.dist-info/LICENSE
reqless-0.13.3.dist-info/METADATA
reqless-0.13.3.dist-info/WHEEL
reqless-0.13.3.dist-info/top_level.txt
reqless-0.13.3.dist-info/RECORD
