Metadata-Version: 2.1
Name: reqless
Version: 0.13.3
Summary: Redis-based Queue Management
Author: Danny Guinther
License: MIT
Project-URL: Homepage, https://github.com/tdg5/reqless-py
Project-URL: Source, https://github.com/tdg5/reqless-py
Project-URL: Tracker, https://github.com/tdg5/reqless-py/issues
Keywords: job,qless,qmore,redis,reqless
Classifier: Intended Audience :: Developers
Classifier: License :: OSI Approved :: MIT License
Classifier: Operating System :: OS Independent
Classifier: Programming Language :: Python :: 3
Classifier: Programming Language :: Python :: 3.10
Classifier: Programming Language :: Python :: 3.11
Classifier: Programming Language :: Python :: 3.9
Requires-Python: >3.9.0
License-File: LICENSE
Requires-Dist: argparse
Requires-Dist: decorator
Requires-Dist: hiredis
Requires-Dist: redis
Requires-Dist: typing-extensions >=4.8.0
Provides-Extra: all
Requires-Dist: reqless[dev,test] ; extra == 'all'
Provides-Extra: dev
Requires-Dist: black ~=24.3 ; extra == 'dev'
Requires-Dist: build ~=1.0.3 ; extra == 'dev'
Requires-Dist: flake8-pyproject ~=1.2.3 ; extra == 'dev'
Requires-Dist: flake8 ~=7.0.0 ; extra == 'dev'
Requires-Dist: gevent ~=24.2.1 ; extra == 'dev'
Requires-Dist: isort ~=5.8.0 ; extra == 'dev'
Requires-Dist: mypy ~=1.8.0 ; extra == 'dev'
Requires-Dist: pre-commit ~=2.20.0 ; extra == 'dev'
Requires-Dist: removestar ~=1.3.1 ; extra == 'dev'
Requires-Dist: safety ==2.3.4 ; extra == 'dev'
Requires-Dist: setproctitle ~=1.3.3 ; extra == 'dev'
Requires-Dist: twine ~=4.0.2 ; extra == 'dev'
Requires-Dist: types-decorator ~=5.1.8.4 ; extra == 'dev'
Requires-Dist: types-mock ~=5.1.0.2 ; extra == 'dev'
Requires-Dist: types-redis ~=4.6.0.11 ; extra == 'dev'
Provides-Extra: test
Requires-Dist: coverage ; extra == 'test'
Requires-Dist: coverage-badge ~=1.1.0 ; extra == 'test'
Requires-Dist: mock ; extra == 'test'
Requires-Dist: pytest ~=7.4.0 ; extra == 'test'
Requires-Dist: setuptools >=69 ; extra == 'test'
